sigsci_site_manager/__init__.py
sigsci_site_manager/__version__.py
sigsci_site_manager/api.py
sigsci_site_manager/backup.py
sigsci_site_manager/clone.py
sigsci_site_manager/consts.py
sigsci_site_manager/deploy.py
sigsci_site_manager/merge.py
sigsci_site_manager/migrate.py
sigsci_site_manager/site_manager.py
sigsci_site_manager/user.py
sigsci_site_manager/util.py
sigsci_site_manager/validate.py
sigsci_site_manager-1.4.0.dist-info/LICENSE
sigsci_site_manager-1.4.0.dist-info/METADATA
sigsci_site_manager-1.4.0.dist-info/WHEEL
sigsci_site_manager-1.4.0.dist-info/entry_points.txt
sigsci_site_manager-1.4.0.dist-info/top_level.txt
sigsci_site_manager-1.4.0.dist-info/RECORD
