Metadata-Version: 2.1
Name: sigsci-site-manager
Version: 1.4.0
Summary: Utility for managing Signal Sciences sites
Home-page: https://github.com/turnerlabs/sigsci_site_manager
Author: Turner ISO
Author-email: isodev@turner.com
License: UNKNOWN
Platform: UNKNOWN
Classifier: Programming Language :: Python :: 3
Classifier: Programming Language :: Python :: 3.6
Classifier: Programming Language :: Python :: 3.7
Classifier: License :: OSI Approved :: Apache Software License
Classifier: Operating System :: OS Independent
Classifier: Development Status :: 5 - Production/Stable
Classifier: Intended Audience :: System Administrators
Classifier: Environment :: Console
Classifier: Topic :: Security
Requires-Dist: pysigsci (>=3.10.0)
